squatspotter/__init__.py
squatspotter/cli.py
squatspotter/core.py
squatspotter/dnschecker.py
squatspotter/listMaker.py
squatspotter/notifications.py
squatspotter/reporting.py
squatspotter/utils.py
squatspotter-1.0.0.dist-info/METADATA
squatspotter-1.0.0.dist-info/WHEEL
squatspotter-1.0.0.dist-info/entry_points.txt
squatspotter-1.0.0.dist-info/top_level.txt
squatspotter-1.0.0.dist-info/RECORD
